pycountry/__init__.py
pycountry/db.py
pycountry/databases/iso15924.json
pycountry/databases/iso3166-1.json
pycountry/databases/iso3166-2.json
pycountry/databases/iso3166-3.json
pycountry/databases/iso4217.json
pycountry/databases/iso639-3.json
pycountry/locales/ab/LC_MESSAGES/iso3166-1.mo
pycountry/locales/ace/LC_MESSAGES/iso3166-1.mo
pycountry/locales/ach/LC_MESSAGES/iso3166-1.mo
pycountry/locales/af/LC_MESSAGES/iso3166-1.mo
pycountry/locales/af/LC_MESSAGES/iso3166-3.mo
pycountry/locales/af/LC_MESSAGES/iso3166.mo
pycountry/locales/af/LC_MESSAGES/iso639-3.mo
pycountry/locales/af/LC_MESSAGES/iso639_3.mo
pycountry/locales/ak/LC_MESSAGES/iso3166-1.mo
pycountry/locales/am/LC_MESSAGES/iso3166-1.mo
pycountry/locales/am/LC_MESSAGES/iso3166-3.mo
pycountry/locales/am/LC_MESSAGES/iso3166.mo
pycountry/locales/am/LC_MESSAGES/iso639-3.mo
pycountry/locales/am/LC_MESSAGES/iso639_3.mo
pycountry/locales/an/LC_MESSAGES/iso3166-1.mo
pycountry/locales/ar/LC_MESSAGES/iso15924.mo
pycountry/locales/ar/LC_MESSAGES/iso3166-1.mo
pycountry/locales/ar/LC_MESSAGES/iso3166-3.mo
pycountry/locales/ar/LC_MESSAGES/iso3166.mo
pycountry/locales/ar/LC_MESSAGES/iso639-3.mo
pycountry/locales/ar/LC_MESSAGES/iso639_3.mo
pycountry/locales/as/LC_MESSAGES/iso3166-1.mo
pycountry/locales/as/LC_MESSAGES/iso3166-3.mo
pycountry/locales/as/LC_MESSAGES/iso3166.mo
pycountry/locales/ast/LC_MESSAGES/iso3166-1.mo
pycountry/locales/ast/LC_MESSAGES/iso3166-3.mo
pycountry/locales/ast/LC_MESSAGES/iso3166.mo
pycountry/locales/ast/LC_MESSAGES/iso639-3.mo
pycountry/locales/ast/LC_MESSAGES/iso639_3.mo
pycountry/locales/ay/LC_MESSAGES/iso3166-1.mo
pycountry/locales/az/LC_MESSAGES/iso3166-1.mo
pycountry/locales/az/LC_MESSAGES/iso3166-2.mo
pycountry/locales/az/LC_MESSAGES/iso3166-3.mo
pycountry/locales/az/LC_MESSAGES/iso3166.mo
pycountry/locales/az/LC_MESSAGES/iso3166_2.mo
pycountry/locales/az/LC_MESSAGES/iso639-3.mo
pycountry/locales/az/LC_MESSAGES/iso639_3.mo
pycountry-18.5.26.dist-info/DESCRIPTION.rst
pycountry-18.5.26.dist-info/METADATA
pycountry-18.5.26.dist-info/RECORD
pycountry-18.5.26.dist-info/WHEEL
pycountry-18.5.26.dist-info/metadata.json
pycountry-18.5.26.dist-info/top_level.txt
