Metadata-Version: 1.1
Name: pycountry
Version: 18.5.26
Summary: ISO country, subdivision, language, currency and script definitions and their translations
Home-page: UNKNOWN
Author: Christian Theune
Author-email: ct@flyingcircus.io
License: LGPL 2.1
Keywords: country subdivision language currency iso 3166 639 4217 15924 3166-2
Platform: UNKNOWN
Classifier: Development Status :: 5 - Production/Stable
Classifier: Intended Audience :: Developers
Classifier: Intended Audience :: Information Technology
Classifier: License :: OSI Approved :: GNU Lesser General Public License v2 (LGPLv2)
Classifier: Operating System :: OS Independent
Classifier: Programming Language :: Python
Classifier: Programming Language :: Python :: 2
Classifier: Programming Language :: Python :: 2.6
Classifier: Programming Language :: Python :: 2.7
Classifier: Programming Language :: Python :: 3
Classifier: Programming Language :: Python :: 3.3
Classifier: Programming Language :: Python :: 3.4
Classifier: Programming Language :: Python :: 3.5
Classifier: Topic :: Software Development :: Internationalization
Classifier: Topic :: Software Development :: Localization
